<cricbuzz_live><match><team>DC</team><score>146-4(14)</score><status>Delhi Capitals need 97 runs in 36 balls</status><last_updated>05:23:04 PM</last_updated></match><batting><player><name>Sameer Rizvi </name><runs>28</runs><balls>15</balls><sr>186.67</sr></player><player><name>Tristan Stubbs</name><runs>11</runs><balls>9</balls><sr>122.22</sr></player><player><name>Sakib Hussain </name><runs>2</runs><balls>0</balls><sr>7.00</sr></player><player><name>Nitish Kumar Reddy</name><runs>4</runs><balls>0</balls><sr>14.25</sr></player></batting></cricbuzz_live>